PopcornGL/__init__.py
PopcornGL/popcorngl.py
popcorngl-4.dist-info/LICENSE
popcorngl-4.dist-info/METADATA
popcorngl-4.dist-info/WHEEL
popcorngl-4.dist-info/top_level.txt
popcorngl-4.dist-info/RECORD
