Metadata-Version: 2.1
Name: popcorngl
Version: 4
Summary: Simple graphics language for python.
Home-page: https://github.com/Gpopcorn/PopcornGL
Author: Gpopcorn
License: UNKNOWN
Project-URL: Bug Tracker, https://github.com/Gpopcorn/PopcornGL/issues
Platform: UNKNOWN
Classifier: Programming Language :: Python :: 3
Classifier: License :: OSI Approved :: MIT License
Classifier: Operating System :: OS Independent
Requires-Python: >=3.9
License-File: LICENSE
